README
setup.py
pysubtitles.egg-info/PKG-INFO
pysubtitles.egg-info/SOURCES.txt
pysubtitles.egg-info/dependency_links.txt
pysubtitles.egg-info/not-zip-safe
pysubtitles.egg-info/requires.txt
pysubtitles.egg-info/top_level.txt
subtitles/__init__.py
