Metadata-Version: 1.0
Name: pysubtitles
Version: 0.2
Summary: Python Subtitle Class
Home-page: http://oil21.org/~j/code/pysubtitles
Author: j
Author-email: j@oil21.org
License: GPLv3
Download-URL: http://oil21.org/~j/code/pysubtitles/download
Platform: UNKNOWN
Classifier: Development Status :: 4 - Beta
Classifier: Operating System :: OS Independent
Classifier: Programming Language :: Python
Classifier: Topic :: Software Development :: Libraries :: Python Modules
Classifier: License :: OSI Approved :: GNU General Public License (GPL)
